setup.py
bkrypt/__init__.py
bkrypt/version.py
bkrypt.egg-info/PKG-INFO
bkrypt.egg-info/SOURCES.txt
bkrypt.egg-info/dependency_links.txt
bkrypt.egg-info/not-zip-safe
bkrypt.egg-info/requires.txt
bkrypt.egg-info/top_level.txt